pistyle/__init__.py
pistyle/utils.py
pistyle-0.1.2.dist-info/METADATA
pistyle-0.1.2.dist-info/WHEEL
pistyle-0.1.2.dist-info/top_level.txt
pistyle-0.1.2.dist-info/RECORD
